orchestration_utils/__init__.py
orchestration_utils/aws.py
orchestration_utils/copy_into_s3.py
orchestration_utils/etl_control.py
orchestration_utils/etl_operations.py
orchestration_utils/notifications.py
orchestration_utils/queries.py
orchestration_utils-0.0.16.dist-info/METADATA
orchestration_utils-0.0.16.dist-info/WHEEL
orchestration_utils-0.0.16.dist-info/top_level.txt
orchestration_utils-0.0.16.dist-info/RECORD
