Metadata-Version: 2.4
Name: orchestration_utils
Version: 0.0.16
Summary: This package contains utility functions for Prefect and Snowflake
Author-email: DWBI <dwbi@cloudfactory.com>
License-Expression: BSD-1-Clause
Project-URL: Repository, https://github.com/cloudfactory/orchestration-utilities
Classifier: Programming Language :: Python :: 3
Classifier: Operating System :: OS Independent
Requires-Python: >=3.11
Requires-Dist: pandas==2.3.3
Requires-Dist: numpy==1.26.4
Requires-Dist: prefect-aws==0.5.1
Requires-Dist: prefect-snowflake==0.28.5
Requires-Dist: pyarrow==22.0.0
Requires-Dist: pydantic==2.12.5
Requires-Dist: requests==2.32.5
Requires-Dist: prefect==3.6.8
